wa_cli/__init__.py
wa_cli/_import.py
wa_cli/_version.py
wa_cli/docker_cli.py
wa_cli/script.py
wa_cli/wa.py
wa_cli/wiki.py
wa_cli/scripts/__init__.py
wa_cli/scripts/licenseheaders.py
wa_cli/utils/__init__.py
wa_cli/utils/dependencies.py
wa_cli/utils/files.py
wa_cli/utils/json.py
wa_cli/utils/logger.py
wa_cli-0.2.7.dist-info/LICENSE
wa_cli-0.2.7.dist-info/METADATA
wa_cli-0.2.7.dist-info/WHEEL
wa_cli-0.2.7.dist-info/entry_points.txt
wa_cli-0.2.7.dist-info/top_level.txt
wa_cli-0.2.7.dist-info/RECORD
