Metadata-Version: 2.1
Name: wa-cli
Version: 0.2.7
Summary: Wisconsin Autonomous Command Line Interface Tool
Home-page: UNKNOWN
Author: Wisconsin Autonomous
Author-email: wisconsinautonomous@studentorg.wisc.edu
License: MIT
Project-URL: Homepage, https://github.com/WisconsinAutonomous/wa_cli/
Project-URL: Bug Reports, https://github.com/WisconsinAutonomous/wa_cli/issues
Project-URL: Source Code, https://github.com/WisconsinAutonomous/wa_cli/
Project-URL: Our Team!, https://wa.wisc.edu
Platform: UNKNOWN
Classifier: Development Status :: 3 - Alpha
Classifier: Topic :: Software Development
Classifier: License :: OSI Approved :: MIT License
Classifier: Programming Language :: Python :: 3
Requires-Python: >=3.6, <4
License-File: LICENSE
Requires-Dist: sphinx-argparse
Requires-Dist: python-on-whales
Requires-Dist: colorlog
Requires-Dist: avtoolbox
